pdf2csv/__init__.py
pdf2csv/cli.py
pdf2csv/converter.py
pdf2csv/helpers.py
pdf2csv-0.2.2.dist-info/LICENSE
pdf2csv-0.2.2.dist-info/METADATA
pdf2csv-0.2.2.dist-info/WHEEL
pdf2csv-0.2.2.dist-info/entry_points.txt
pdf2csv-0.2.2.dist-info/top_level.txt
pdf2csv-0.2.2.dist-info/RECORD
