Metadata-Version: 2.1
Name: pdf2csv
Version: 0.2.2
Summary: A python library and CLI tool to convert PDF files to CSV files.
Author-email: Mehdi Ghodsizadeh <mehdi.ghodsizadeh@gmail.com>
License: MIT License
Project-URL: Homepage, https://github.com/ghodsizadeh/pdf2csv
Project-URL: Issues, https://github.com/ghodsizadeh/pdf2csv/issues
Project-URL: Repository, https://github.com/ghodsizadeh/pdf2csv.git
Keywords: pdf,csv,excel,pdf2csv,data extraction,docling
Classifier: Development Status :: 3 - Alpha
Classifier: Intended Audience :: Developers
Classifier: License :: OSI Approved :: MIT License
Classifier: Programming Language :: Python :: 3
Classifier: Programming Language :: Python :: 3.10
Classifier: Programming Language :: Python :: 3.11
Classifier: Programming Language :: Python :: 3.12
Classifier: Programming Language :: Python :: 3.13
Requires-Python: >=3.10
License-File: LICENSE
Requires-Dist: docling>=2.14.0
Requires-Dist: typer>=0.12.5
